[
  {
    "file": "./articles/超算队招新.md",
    "title": "超算队招新题",
    "excerpt": "对于超算队招新题的解答过程的记录，包括具体操作和配置的步骤。",
    "date": "2026-02-24",
    "category": "实操记录",
    "tags": ["计算机", "HPC"]
  },
  {
    "file": "./articles/计组.md",
    "title": "计组期末复习",
    "excerpt": "期末复习的内容，只针对考试范围进行整理。",
    "date": "2026-01-02",
    "category": "课内学习",
    "tags": ["计算机"]
  },
  {
    "file": "./articles/马原.md",
    "title": "马原期末复习",
    "excerpt": "对课本的一些摘录。",
    "date": "2025-12-29",
    "category": "课内学习",
    "tags": ["思想政治"]
  },
  {
    "file": "./articles/概统.md",
    "title": "概率论与数理统计",
    "excerpt": "快速过一遍概率论与数理统计的重点内容。",
    "date": "2025-12-27",
    "category": "课内学习",
    "tags": ["数学", "概率论"]
  }
]